qsv/__init__.py
qsv/count.py
qsv/sample.py
qsv/slice.py
qsv/table.py
qsv_duct-0.0.1.dist-info/WHEEL
qsv_duct-0.0.1.dist-info/METADATA
qsv_duct-0.0.1.dist-info/RECORD
