Metadata-Version: 2.1
Name: qsv-duct
Version: 0.0.1
Summary: Python wrapper based on the qsv CLI tool
Keywords: qsv,csv
Author: Mueez Khan
Requires-Dist: duct
Requires-Dist: pytest ; extra == "test"
Project-URL: Home, https://github.com/rzmk/qsv-duct
Provides-Extra: test
